apidb/__init__.py
apidb/apidb_core.py
apidb-0.2.1.dist-info/LICENSE
apidb-0.2.1.dist-info/METADATA
apidb-0.2.1.dist-info/WHEEL
apidb-0.2.1.dist-info/top_level.txt
apidb-0.2.1.dist-info/RECORD
