Metadata-Version: 2.1
Name: apidb
Version: 0.2.1
Summary: Autogenerate API based on DB structure directly from Python using ORM
Home-page: https://github.com/DovaX/apidb
Author: DovaX
Author-email: dovax.ai@gmail.com
License: UNKNOWN
Platform: UNKNOWN
Classifier: Programming Language :: Python :: 3
Classifier: License :: OSI Approved :: MIT License
Classifier: Operating System :: OS Independent
Requires-Python: >=3.6
License-File: LICENSE
Requires-Dist: fastapi
Requires-Dist: flask
Requires-Dist: dbhydra
